django_i3tasks/__init__.py
django_i3tasks/admin.py
django_i3tasks/apps.py
django_i3tasks/exceptions.py
django_i3tasks/models.py
django_i3tasks/tasks.py
django_i3tasks/tests.py
django_i3tasks/types.py
django_i3tasks/urls.py
django_i3tasks/utils.py
django_i3tasks/views.py
django_i3tasks/management/__init__.py
django_i3tasks/management/commands/__init__.py
django_i3tasks/management/commands/i3tasks_ensure_pubsub.py
django_i3tasks/migrations/0001_initial.py
django_i3tasks/migrations/0002_rename_created_taskexecution_created_at_and_more.py
django_i3tasks/migrations/0003_alter_taskexecutiontry_finished_at_and_more.py
django_i3tasks/migrations/0004_alter_taskexecutionresult_task_execution_try.py
django_i3tasks/migrations/__init__.py
django_i3tasks/queue_manager/__init__.py
django_i3tasks/queue_manager/google_pubsub.py
django_i3tasks-0.0.25.dist-info/LICENSE
django_i3tasks-0.0.25.dist-info/METADATA
django_i3tasks-0.0.25.dist-info/WHEEL
django_i3tasks-0.0.25.dist-info/top_level.txt
django_i3tasks-0.0.25.dist-info/RECORD
