Metadata-Version: 2.1
Name: django-i3tasks
Version: 0.0.25
Summary: Django app for manage async tasks by http requests
Home-page: https://github.com/sajlx/django-i3tasks
Author: Ivan Bettarini
Author-email: ivan.bettarini@gmail.com
License: GNU General Public License v3.0
Classifier: Environment :: Web Environment
Classifier: Operating System :: OS Independent
Classifier: Development Status :: 3 - Alpha
Classifier: Intended Audience :: Developers
Classifier: Programming Language :: Python :: 3
Classifier: Framework :: Django
License-File: LICENSE
Requires-Dist: django
Requires-Dist: djangorestframework
Requires-Dist: requests
Requires-Dist: croniter >=2.0.1
